Struts2RumenV30DamoGuyan/README.md
Struts2RumenV30DamoGuyan/__init__.py
Struts2RumenV30DamoGuyan/__main__.py
Struts2RumenV30DamoGuyan/file.pdf
Struts2RumenV30DamoGuyan/index.html
struts2_rumen_v3_0_damo_guyan-2024.3.2.0.dist-info/METADATA
struts2_rumen_v3_0_damo_guyan-2024.3.2.0.dist-info/WHEEL
struts2_rumen_v3_0_damo_guyan-2024.3.2.0.dist-info/entry_points.txt
struts2_rumen_v3_0_damo_guyan-2024.3.2.0.dist-info/top_level.txt
struts2_rumen_v3_0_damo_guyan-2024.3.2.0.dist-info/RECORD
